p4adev_recipes/__init__.py
p4adev_recipes/bundle_installer.py
p4adev_recipes/recipe/__init__.py
p4adev_recipes/recipe/adv_cc_recipe.py
p4adev_recipes/recipe/build_tool_recipe.py
p4adev_recipes/recipe/no_setup_pypi_recipe.py
p4adev_recipes-0.0.3.dist-info/LICENSE
p4adev_recipes-0.0.3.dist-info/METADATA
p4adev_recipes-0.0.3.dist-info/WHEEL
p4adev_recipes-0.0.3.dist-info/RECORD
