Metadata-Version: 2.1
Name: p4adev_recipes
Version: 0.0.3
Summary: Some advanced recipes bases for python-for-android projects.
License: Apache 2.0
Author: BlackCatDevel0per
Author-email: bcdev@mail.ru
Requires-Python: >=3.8.1,<4.0
Classifier: License :: Other/Proprietary License
Classifier: Programming Language :: Python :: 3
Classifier: Programming Language :: Python :: 3.9
Classifier: Programming Language :: Python :: 3.10
Classifier: Programming Language :: Python :: 3.11
Classifier: Programming Language :: Python :: 3.12
Requires-Dist: installer (>=0.7.0,<0.8.0)
Project-URL: Depository, https://github.com/BlackCatDevel0per/p4adev_recipes
Project-URL: Homepage, https://github.com/BlackCatDevel0per/p4adev_recipes
Project-URL: Repository, https://github.com/BlackCatDevel0per/p4adev_recipes
